pyff/__init__.py
pyff/classes.py
pyff/directories.py
pyff/functions.py
pyff/imports.py
pyff/kitchensink.py
pyff/modules.py
pyff/packages.py
pyff/repositories.py
pyff/run.py
pyff/statements.py
pyff/summary.py
pythondiff-0.7.0.dist-info/METADATA
pythondiff-0.7.0.dist-info/RECORD
pythondiff-0.7.0.dist-info/WHEEL
pythondiff-0.7.0.dist-info/entry_points.txt
pythondiff-0.7.0.dist-info/top_level.txt
