Metadata-Version: 2.1
Name: pythondiff
Version: 0.7.0
Summary: Python Diff
Home-page: https://github.com/petr-muller/pyff
Author: Petr Muller
Author-email: afri@afri.cz
License: UNKNOWN
Keywords: python static_analysis diff
Platform: UNKNOWN
Classifier: Development Status :: 4 - Beta
Classifier: Intended Audience :: Developers
Classifier: Topic :: Software Development :: Quality Assurance
Classifier: Programming Language :: Python :: 3
Classifier: Programming Language :: Python :: 3.6
Classifier: Programming Language :: Python :: 3.7
Classifier: License :: OSI Approved :: Apache Software License
Requires-Dist: colorama
Requires-Dist: astroid
Requires-Dist: gitpython
